ngxtop/__init__.py
ngxtop/config_parser.py
ngxtop/ngxtop.py
ngxtop/utils.py
ngxtop-0.0.3.dist-info/LICENSE.txt
ngxtop-0.0.3.dist-info/METADATA
ngxtop-0.0.3.dist-info/WHEEL
ngxtop-0.0.3.dist-info/entry_points.txt
ngxtop-0.0.3.dist-info/top_level.txt
ngxtop-0.0.3.dist-info/RECORD
