Metadata-Version: 2.1
Name: ngxtop
Version: 0.0.3
Summary: Real-time metrics for nginx server
Home-page: https://github.com/lebinh/ngxtop
Author: Binh Le
Author-email: lebinh.it@gmail.com
License: MIT
Keywords: cli monitoring nginx system
Platform: UNKNOWN
Classifier: Development Status :: 4 - Beta
Classifier: License :: OSI Approved :: MIT License
Classifier: Environment :: Console
Classifier: Intended Audience :: Developers
Classifier: Intended Audience :: System Administrators
Classifier: Programming Language :: Python :: 2
Classifier: Programming Language :: Python :: 2.6
Classifier: Programming Language :: Python :: 2.7
Classifier: Programming Language :: Python :: 3
Classifier: Programming Language :: Python :: 3.2
Classifier: Programming Language :: Python :: 3.3
Requires-Dist: docopt
Requires-Dist: tabulate
Requires-Dist: pyparsing
